chiquito-0.2.0.dist-info/METADATA
chiquito-0.2.0.dist-info/WHEEL
chiquito/wit_gen.py
chiquito/query.py
chiquito/dsl.py
chiquito/__init__.py
chiquito/cb.py
chiquito/expr.py
chiquito/util.py
chiquito/chiquito_ast.py
chiquito/rust_chiquito.cpython-37m-arm-linux-gnueabihf.so
chiquito-0.2.0.dist-info/RECORD
