Metadata-Version: 2.1
Name: chiquito
Version: 0.2.0
Classifier: Programming Language :: Rust
Classifier: Programming Language :: Python :: Implementation :: CPython
Classifier: Programming Language :: Python :: Implementation :: PyPy
Requires-Dist: py_ecc
Author: Leo Lara <leo@leolara.me>
Author-email: Leo Lara <leo@leolara.me>
License: MIT OR Apache-2.0
Requires-Python: >=3.7
